README.rst
setup.py
tornadohttp/__init__.py
tornadohttp/tornadohttp.py
tornadohttp.egg-info/PKG-INFO
tornadohttp.egg-info/SOURCES.txt
tornadohttp.egg-info/dependency_links.txt
tornadohttp.egg-info/requires.txt
tornadohttp.egg-info/top_level.txt